mkdocs_gen_nav_plugin/__init__.py
mkdocs_gen_nav_plugin/plugin.py
mkdocs_gen_nav_plugin-0.2.0.dist-info/METADATA
mkdocs_gen_nav_plugin-0.2.0.dist-info/WHEEL
mkdocs_gen_nav_plugin-0.2.0.dist-info/entry_points.txt
mkdocs_gen_nav_plugin-0.2.0.dist-info/licenses/LICENSE
mkdocs_gen_nav_plugin-0.2.0.dist-info/RECORD
