Metadata-Version: 2.3
Name: mkdocs-gen-nav-plugin
Version: 0.2.0
Summary: Mkdocs plugin to generate nav list from docs dir
Project-URL: Homepage, https://github.com/vrerv/mkdocs-gen-nav-plugin
Project-URL: Bug Tracker, https://github.com/vrerv/mkdocs-gen-nav-plugin/issues
Author-email: soonoh <soonoh.jung@gmail.com>, FrozenSource <bram.nijenkamp@dataacess.eu>
License-File: LICENSE
Classifier: Intended Audience :: Developers
Classifier: Intended Audience :: Information Technology
Classifier: Programming Language :: Python
Classifier: Programming Language :: Python :: 3 :: Only
Requires-Python: >=3.7
Requires-Dist: mkdocs>=1.4.2
